eudaemon/__init__.py
eudaemon/brightness.py
eudaemon/idleness.py
eudaemon/utils.py
eudaemon-0.1.0.dist-info/LICENSE
eudaemon-0.1.0.dist-info/METADATA
eudaemon-0.1.0.dist-info/WHEEL
eudaemon-0.1.0.dist-info/entry_points.txt
eudaemon-0.1.0.dist-info/RECORD
