Metadata-Version: 2.1
Name: eudaemon
Version: 0.1.0
Summary: Monitor activity and help user to be conscious about it and to take positive action.
Home-page: https://github.com/danisztls/eudaemon
License: GPLv3
Author: Daniel Souza
Author-email: me@posix.dev.br
Requires-Python: >=3.11,<4.0
Classifier: License :: Other/Proprietary License
Classifier: Programming Language :: Python :: 3
Classifier: Programming Language :: Python :: 3.11
Classifier: Programming Language :: Python :: 3.12
Requires-Dist: dbus-fast (>=2.21.1,<3.0.0)
